{"board_tabs":null,"extra":{"now":1699431844000,"fatal_item_ids":[],"logid":"20231108162403A7D6439E0E000B00CA83"},"log_pb":{"impr_id":"20231108162403A7D6439E0E000B00CA83"},"status_code":0,"data":{"word_list":[{"drift_info":null,"aweme_infos":null,"discuss_video_count":1,"article_detail_count":0,"group_id":"7297408285707064639","event_time":1699414052,"related_words":null,"label":3,"can_extend_detail":false,"sentence_tag":20002,"word":"这就是敞篷环绕4D影院","view_count":65718821,"video_count":1,"word_type":1,"sentence_id":"1469537","hotlist_param":"{\"version\":1}","display_style":0,"hot_value":11362651,"word_cover":{"uri":"tos-cn-p-0015/c7fd9651f7aa45b8bc9d91729ea8dc9e_1699359915","url_list":["https://p3-sign.douyinpic.com/tos-cn-p-0015/c7fd9651f7aa45b8bc9d91729ea8dc9e_1699359915~noop.jpeg?x-expires=1699452000&x-signature=sSHC2kcokiMdnRLmM2lpT7papDs%3D&from=3218412987","https://p26-sign.douyinpic.com/tos-cn-p-0015/c7fd9651f7aa45b8bc9d91729ea8dc9e_1699359915~noop.jpeg?x-expires=1699452000&x-signature=gKEC6ByvNxzNZuyS2D8fTERgjq0%3D&from=3218412987","https://p9-sign.douyinpic.com/tos-cn-p-0015/c7fd9651f7aa45b8bc9d91729ea8dc9e_1699359915~noop.jpeg?x-expires=1699452000&x-signature=JAlg%2BpnE2D4F0ocDAhRbnWSXV%2Bk%3D&from=3218412987"]},"position":1,"word_sub_board":null},{"article_detail_count":0,"label":8,"group_id":"7297437999574095143","related_words":null,"view_count":68920026,"display_style":0,"position":2,"word_type":1,"discuss_video_count":1,"word_sub_board":null,"aweme_infos":null,"word":"了不起的中国颜色开播","word_cover":{"uri":"tos-cn-p-0015/95da17cdce73438b8cc3d3883986395e_1698826458","url_list":["https://p26-sign.douyinpic.com/tos-cn-p-0015/95da17cdce73438b8cc3d3883986395e_1698826458~noop.jpeg?x-expires=1699452000&x-signature=8%2FA178hKd21Gij9yQy1oFEiiuKk%3D&from=3218412987","https://p9-sign.douyinpic.com/tos-cn-p-0015/95da17cdce73438b8cc3d3883986395e_1698826458~noop.jpeg?x-expires=1699452000&x-signature=gdYFKTRN7v%2BRQVbBhWiKdqIXt%2F4%3D&from=3218412987","https://p3-sign.douyinpic.com/tos-cn-p-0015/95da17cdce73438b8cc3d3883986395e_1698826458~noop.jpeg?x-expires=1699452000&x-signature=GkqI6MIMY%2F2IldRoFwxiFjuWZsQ%3D&from=3218412987"]},"can_extend_detail":false,"sentence_id":"1469681","event_time":1699421658,"hot_value":10590890,"video_count":16,"drift_info":null,"hotlist_param":"{\"version\":1}","sentence_tag":2003},{"drift_info":null,"hotlist_param":"{\"version\":1}","label":1,"word_type":1,"view_count":67141277,"related_words":null,"aweme_infos":null,"article_detail_count":0,"word_cover":{"uri":"tos-cn-p-0015/2002de45c4e645c4a5bc4383ce593843_1699352908","url_list":["https://p11-sign.douyinpic.com/tos-cn-p-0015/2002de45c4e645c4a5bc4383ce593843_1699352908~noop.jpeg?x-expires=1699452000&x-signature=iqh9MHbEPgH9mZGP31XczttcGU4%3D&from=3218412987","https://p3-sign.douyinpic.com/tos-cn-p-0015/2002de45c4e645c4a5bc4383ce593843_1699352908~noop.jpeg?x-expires=1699452000&x-signature=ZtnN6T85qe%2BJxa5eXJYm4ee4shI%3D&from=3218412987","https://p26-sign.douyinpic.com/tos-cn-p-0015/2002de45c4e645c4a5bc4383ce593843_1699352908~noop.jpeg?x-expires=1699452000&x-signature=L0kdfQY8hzLL%2BA105Dyn8AWWFvQ%3D&from=3218412987"]},"video_count":1,"group_id":"7297165201337079076","display_style":0,"discuss_video_count":1,"word_sub_board":null,"hot_value":10223555,"can_extend_detail":false,"event_time":1699430856,"sentence_tag":4003,"word":"进博会场馆四叶草背后的奥秘","position":3,"sentence_id":"1469959"},{"word_cover":{"uri":"tos-cn-p-0015/1f12864014be48059c8a3f6a5972382e_1699412129","url_list":["https://p6-sign.douyinpic.com/tos-cn-p-0015/1f12864014be48059c8a3f6a5972382e_1699412129~noop.jpeg?x-expires=1699452000&x-signature=Nw9TUShRRaKiWTNOEgheUjjP19I%3D&from=3218412987","https://p9-sign.douyinpic.com/tos-cn-p-0015/1f12864014be48059c8a3f6a5972382e_1699412129~noop.jpeg?x-expires=1699452000&x-signature=PelD1STBN89ExuGOO5Kvl0DGNk4%3D&from=3218412987","https://p3-sign.douyinpic.com/tos-cn-p-0015/1f12864014be48059c8a3f6a5972382e_1699412129~noop.jpeg?x-expires=1699452000&x-signature=t5iEGpnoXnih2PZ3b2Ur3H0bPgo%3D&from=3218412987"]},"word_type":1,"sentence_tag":12000,"aweme_infos":null,"group_id":"7241847939672315140","can_extend_detail":false,"hotlist_param":"{\"version\":1}","event_time":1699416413,"drift_info":null,"display_style":0,"article_detail_count":0,"word":"原神水神芙宁娜上线","hot_value":9474115,"video_count":24,"related_words":null,"view_count":61016049,"discuss_video_count":1,"word_sub_board":null,"label":3,"position":4,"sentence_id":"1469611"},{"group_id":"7297458146749895955","sentence_id":"1469868","sentence_tag":14000,"word":"36岁工程师自学成科普海王","position":5,"video_count":9,"drift_info":null,"aweme_infos":null,"word_sub_board":null,"article_detail_count":0,"label":1,"event_time":1699427503,"view_count":64623851,"hotlist_param":"{\"version\":1}","discuss_video_count":1,"word_cover":{"uri":"tos-cn-p-0015/oolVNcWGjBkIwAe9LAQQzdRAYSAngWbyezGnDo","url_list":["https://p3-sign.douyinpic.com/tos-cn-p-0015/oolVNcWGjBkIwAe9LAQQzdRAYSAngWbyezGnDo~noop.jpeg?x-expires=1699452000&x-signature=ld%2Bzh5nYLbse6qBuvVYwUu2sICE%3D&from=3218412987","https://p26-sign.douyinpic.com/tos-cn-p-0015/oolVNcWGjBkIwAe9LAQQzdRAYSAngWbyezGnDo~noop.jpeg?x-expires=1699452000&x-signature=0Hbw5KGOdXssOLQOTIus6FIlJV4%3D&from=3218412987","https://p11-sign.douyinpic.com/tos-cn-p-0015/oolVNcWGjBkIwAe9LAQQzdRAYSAngWbyezGnDo~noop.jpeg?x-expires=1699452000&x-signature=%2BGkOZXgPGyWJ%2Frl7RmDJyifm%2FQU%3D&from=3218412987"]},"can_extend_detail":false,"related_words":null,"hot_value":9413017,"word_type":1,"display_style":0},{"group_id":"7297459132847887670","event_time":1699421141,"discuss_video_count":1,"word":"中山二院患者家属：踢出群聊属实","label":1,"position":6,"view_count":51464871,"drift_info":null,"hotlist_param":"{\"version\":1}","aweme_infos":null,"word_sub_board":null,"video_count":17,"can_extend_detail":false,"sentence_id":"1469673","article_detail_count":0,"related_words":null,"sentence_tag":4003,"display_style":0,"hot_value":9106267,"word_cover":{"uri":"tos-cn-p-0015/80cedb10e97445148c89e8ed8f0d426f_1699423192","url_list":["https://p26-sign.douyinpic.com/tos-cn-p-0015/80cedb10e97445148c89e8ed8f0d426f_1699423192~noop.jpeg?x-expires=1699452000&x-signature=050iJo6zEoy5THVMBDNYDxuOGxk%3D&from=3218412987","https://p6-sign.douyinpic.com/tos-cn-p-0015/80cedb10e97445148c89e8ed8f0d426f_1699423192~noop.jpeg?x-expires=1699452000&x-signature=9w9uMvxPbsngoSJ2ryFEFhSCZqI%3D&from=3218412987","https://p3-sign.douyinpic.com/tos-cn-p-0015/80cedb10e97445148c89e8ed8f0d426f_1699423192~noop.jpeg?x-expires=1699452000&x-signature=ovP5YZkHinf%2F16yXoOLtjRPybHc%3D&from=3218412987"]},"word_type":1},{"word_cover":{"uri":"tos-cn-p-0015/b107ba7f779d4202a14f2bf4af1f46f1_1699406945","url_list":["https://p9-sign.douyinpic.com/tos-cn-p-0015/b107ba7f779d4202a14f2bf4af1f46f1_1699406945~noop.jpeg?x-expires=1699452000&x-signature=w8%2FobmSHKPINnAxMFkQ4XP357ZM%3D&from=3218412987","https://p3-sign.douyinpic.com/tos-cn-p-0015/b107ba7f779d4202a14f2bf4af1f46f1_1699406945~noop.jpeg?x-expires=1699452000&x-signature=pBbVQRmPrCw%2BUPDBevbZsmdOXb0%3D&from=3218412987","https://p26-sign.douyinpic.com/tos-cn-p-0015/b107ba7f779d4202a14f2bf4af1f46f1_1699406945~noop.jpeg?x-expires=1699452000&x-signature=psxLZTvD%2BBRE6W5mK30cASRZcGQ%3D&from=3218412987"]},"video_count":4,"aweme_infos":null,"display_style":0,"word":"以军称已进入加沙城中心地带","position":7,"can_extend_detail":false,"word_type":1,"hotlist_param":"{\"version\":1}","sentence_tag":21000,"group_id":"7297316803368949011","sentence_id":"1469369","discuss_video_count":1,"article_detail_count":0,"label":0,"hot_value":8982134,"event_time":1699407206,"related_words":null,"view_count":56009468,"drift_info":null,"word_sub_board":null},{"video_count":1,"article_detail_count":0,"position":8,"word_cover":{"uri":"tos-cn-p-0015/ee7f2df1e52e4142b38b20d5cbc48ee7_1699406216","url_list":["https://p3-sign.douyinpic.com/tos-cn-p-0015/ee7f2df1e52e4142b38b20d5cbc48ee7_1699406216~noop.jpeg?x-expires=1699452000&x-signature=FTpE7JSlU8uJxEKISIIdCrPof%2Bs%3D&from=3218412987","https://p9-sign.douyinpic.com/tos-cn-p-0015/ee7f2df1e52e4142b38b20d5cbc48ee7_1699406216~noop.jpeg?x-expires=1699452000&x-signature=yUktoPC%2FDirubvrGxPgy4fwprxg%3D&from=3218412987","https://p26-sign.douyinpic.com/tos-cn-p-0015/ee7f2df1e52e4142b38b20d5cbc48ee7_1699406216~noop.jpeg?x-expires=1699452000&x-signature=7NQtvuWw8Is1eWCYOWERBYyoSsk%3D&from=3218412987"]},"group_id":"7298279258219517236","can_extend_detail":false,"view_count":56168646,"aweme_infos":null,"word_sub_board":null,"label":0,"word_type":1,"event_time":1699422816,"related_words":null,"drift_info":null,"word":"大学生雪地作画致敬亚运","sentence_id":"1469711","hotlist_param":"{\"version\":1}","sentence_tag":15000,"display_style":0,"discuss_video_count":1,"hot_value":8915086},{"word_type":1,"sentence_id":"1469829","related_words":null,"view_count":54045734,"discuss_video_count":1,"emo_label":0,"word_cover":{"uri":"tos-cn-p-0015/9682dce1ed3f4ec8acf969fec70de81f_1699426556","url_list":["https://p11-sign.douyinpic.com/tos-cn-p-0015/9682dce1ed3f4ec8acf969fec70de81f_1699426556~noop.jpeg?x-expires=1699452000&x-signature=XuYt63hHFgIA4jJ0fG7lnrF0nXM%3D&from=3218412987","https://p26-sign.douyinpic.com/tos-cn-p-0015/9682dce1ed3f4ec8acf969fec70de81f_1699426556~noop.jpeg?x-expires=1699452000&x-signature=ehKz8lrVMrjdFbZjmpITlkezTss%3D&from=3218412987","https://p6-sign.douyinpic.com/tos-cn-p-0015/9682dce1ed3f4ec8acf969fec70de81f_1699426556~noop.jpeg?x-expires=1699452000&x-signature=ySe2KnxTlkcKZivZENyI64Fzp0I%3D&from=3218412987"]},"video_count":1,"drift_info":null,"hotlist_param":"{\"version\":1}","word_sub_board":null,"article_detail_count":0,"hot_value":8877380,"event_time":1699426104,"group_id":"7298341724559922447","aweme_infos":null,"sentence_tag":7000,"word":"中国平安辟谣入股碧桂园","label":16,"display_style":0,"position":9,"can_extend_detail":false},{"word":"今年流行“冰冻裤”","label":0,"video_count":4,"hotlist_param":"{\"version\":1}","position":10,"word_type":1,"sentence_id":"1469055","sentence_tag":16000,"discuss_video_count":1,"word_cover":{"uri":"tos-cn-p-0015/osJ3AkPCKIKN5NrmIa2C7e24Rve8DhBLAHBf0E","url_list":["https://p26-sign.douyinpic.com/tos-cn-p-0015/osJ3AkPCKIKN5NrmIa2C7e24Rve8DhBLAHBf0E~noop.jpeg?x-expires=1699452000&x-signature=GqYMeQNKdVdvidfrWFIGqZ4w8GY%3D&from=3218412987","https://p3-sign.douyinpic.com/tos-cn-p-0015/osJ3AkPCKIKN5NrmIa2C7e24Rve8DhBLAHBf0E~noop.jpeg?x-expires=1699452000&x-signature=GVphgVMssNgTTEbiY1QXajmpDNg%3D&from=3218412987","https://p6-sign.douyinpic.com/tos-cn-p-0015/osJ3AkPCKIKN5NrmIa2C7e24Rve8DhBLAHBf0E~noop.jpeg?x-expires=1699452000&x-signature=FlM%2BROVhxvKELVpDzASgsKLsDi4%3D&from=3218412987"]},"can_extend_detail":false,"display_style":0,"word_sub_board":null,"article_detail_count":0,"aweme_infos":null,"hot_value":8799808,"group_id":"7298494143617193252","event_time":1699364810,"related_words":null,"view_count":52952801,"drift_info":null},{"video_count":2,"can_extend_detail":false,"view_count":49493781,"word_sub_board":null,"article_detail_count":0,"sentence_id":"1469539","related_words":null,"hotlist_param":"{\"version\":1}","display_style":0,"word":"浙江多地出现大量臭屁虫","group_id":"7296827361160631603","word_type":1,"drift_info":null,"aweme_infos":null,"sentence_tag":4004,"discuss_video_count":1,"label":3,"hot_value":8785393,"word_cover":{"uri":"tos-cn-i-0813c001/owxh9HU1lQCAAAAJ9CS8fE3DgTnAKfA7vgbK7D","url_list":["https://p26-sign.douyinpic.com/tos-cn-i-0813c001/owxh9HU1lQCAAAAJ9CS8fE3DgTnAKfA7vgbK7D~noop.jpeg?x-expires=1699452000&x-signature=%2B%2B%2BSnwznMsSjPYUyT97Y0vCJL7A%3D&from=3218412987","https://p9-sign.douyinpic.com/tos-cn-i-0813c001/owxh9HU1lQCAAAAJ9CS8fE3DgTnAKfA7vgbK7D~noop.jpeg?x-expires=1699452000&x-signature=o%2FmR9gVjQSOsnyjG6b2kGr%2FjFnM%3D&from=3218412987","https://p11-sign.douyinpic.com/tos-cn-i-0813c001/owxh9HU1lQCAAAAJ9CS8fE3DgTnAKfA7vgbK7D~noop.jpeg?x-expires=1699452000&x-signature=v%2Bh7Ns8aFRkCSMCHf%2B4e7%2F4s2Vg%3D&from=3218412987"]},"position":11,"event_time":1699414206},{"event_time":1699414453,"group_id":"7297178060062233919","can_extend_detail":false,"word_type":1,"sentence_id":"1469544","related_words":null,"display_style":0,"word":"我本是高山女孩呐喊又燃又好哭","word_cover":{"uri":"tos-cn-p-0015/21ecd9dc341741bbb08c61cd2f032849_1699409780","url_list":["https://p3-sign.douyinpic.com/tos-cn-p-0015/21ecd9dc341741bbb08c61cd2f032849_1699409780~noop.jpeg?x-expires=1699452000&x-signature=z1YrIKPvVXoEbzuLNjPjxlwiJrU%3D&from=3218412987","https://p26-sign.douyinpic.com/tos-cn-p-0015/21ecd9dc341741bbb08c61cd2f032849_1699409780~noop.jpeg?x-expires=1699452000&x-signature=iSp%2BP%2BM8JK1uGlF2JzWn%2BXvSmmk%3D&from=3218412987","https://p9-sign.douyinpic.com/tos-cn-p-0015/21ecd9dc341741bbb08c61cd2f032849_1699409780~noop.jpeg?x-expires=1699452000&x-signature=2wlbWQvNkaDmMt2EB0H6BKgNtu4%3D&from=3218412987"]},"discuss_video_count":1,"video_count":15,"view_count":46571071,"drift_info":null,"hotlist_param":"{\"version\":1}","sentence_tag":2001,"label":5,"hot_value":8776186,"word_sub_board":null,"article_detail_count":0,"position":12,"aweme_infos":null},{"word":"任素汐王招君听哭了多少人","group_id":"7297470937154163980","aweme_infos":null,"discuss_video_count":1,"word_sub_board":[3],"article_detail_count":0,"video_count":124,"related_words":null,"view_count":51939098,"sentence_tag":1002,"label":9,"word_cover":{"uri":"tos-cn-i-0813/oweA4b1OWga9nrAQAaWDAmCNqAReIMw6lFXRAC","url_list":["https://p26-sign.douyinpic.com/tos-cn-i-0813/oweA4b1OWga9nrAQAaWDAmCNqAReIMw6lFXRAC~noop.jpeg?x-expires=1699452000&x-signature=WThVu3veQUhVXhRfcjtP6JLAsJI%3D&from=3218412987","https://p11-sign.douyinpic.com/tos-cn-i-0813/oweA4b1OWga9nrAQAaWDAmCNqAReIMw6lFXRAC~noop.jpeg?x-expires=1699452000&x-signature=chnI8%2B%2B3Fcg8tDtrydhVXTx1ZHA%3D&from=3218412987","https://p3-sign.douyinpic.com/tos-cn-i-0813/oweA4b1OWga9nrAQAaWDAmCNqAReIMw6lFXRAC~noop.jpeg?x-expires=1699452000&x-signature=7dM3lSQ%2BjRnMjJhaQ3l0J4CCKN4%3D&from=3218412987"]},"position":13,"drift_info":null,"display_style":0,"hot_value":8730232,"can_extend_detail":false,"word_type":1,"sentence_id":"1469694","event_time":1699422012,"hotlist_param":"{\"version\":1}"},{"event_time":1699429180,"related_words":null,"view_count":46941245,"word_sub_board":null,"can_extend_detail":false,"drift_info":null,"hotlist_param":"{\"version\":1}","article_detail_count":0,"word":"看海的热情","hot_value":8725265,"word_cover":{"uri":"tos-cn-p-0015/88900baa1f984bc0952a9a142f2d09aa_1699404259","url_list":["https://p3-sign.douyinpic.com/tos-cn-p-0015/88900baa1f984bc0952a9a142f2d09aa_1699404259~noop.jpeg?x-expires=1699452000&x-signature=zy%2BrXubir6WMYDA3luFwahOl5ME%3D&from=3218412987","https://p26-sign.douyinpic.com/tos-cn-p-0015/88900baa1f984bc0952a9a142f2d09aa_1699404259~noop.jpeg?x-expires=1699452000&x-signature=BLH5105sGWE5TjO0kDSxUENW%2B1E%3D&from=3218412987","https://p11-sign.douyinpic.com/tos-cn-p-0015/88900baa1f984bc0952a9a142f2d09aa_1699404259~noop.jpeg?x-expires=1699452000&x-signature=GHyiCl1nW%2FhrjGBgU2kBKCFOZPE%3D&from=3218412987"]},"position":14,"group_id":"6816735197900395783","word_type":1,"sentence_id":"1469916","sentence_tag":10000,"label":1,"display_style":0,"aweme_infos":null,"discuss_video_count":1,"video_count":1},{"sentence_id":"1469800","related_words":null,"view_count":45258112,"hotlist_param":"{\"version\":1}","discuss_video_count":1,"word":"魏大勋黑西装贵公子","group_id":"7298867696665351435","can_extend_detail":false,"sentence_tag":2008,"article_detail_count":0,"word_cover":{"uri":"tos-cn-p-0015/27e5ff135ee5455f8395517afd7f917b_1699418848","url_list":["https://p3-sign.douyinpic.com/tos-cn-p-0015/27e5ff135ee5455f8395517afd7f917b_1699418848~noop.jpeg?x-expires=1699452000&x-signature=QjQuIGDyGGZI1R7JJI3b5Q93asI%3D&from=3218412987","https://p26-sign.douyinpic.com/tos-cn-p-0015/27e5ff135ee5455f8395517afd7f917b_1699418848~noop.jpeg?x-expires=1699452000&x-signature=Nc0Cm7S0oPjgbad8MrAu4cBFP6g%3D&from=3218412987","https://p11-sign.douyinpic.com/tos-cn-p-0015/27e5ff135ee5455f8395517afd7f917b_1699418848~noop.jpeg?x-expires=1699452000&x-signature=fFu1wPTwCSky387A1dqMAvX1CK0%3D&from=3218412987"]},"video_count":1,"drift_info":null,"aweme_infos":null,"display_style":0,"label":1,"position":15,"word_type":1,"hot_value":8721015,"event_time":1699425245,"word_sub_board":null},{"hot_value":8710311,"display_style":0,"word_sub_board":null,"position":16,"video_count":7,"sentence_id":"1469742","related_words":null,"aweme_infos":null,"discuss_video_count":1,"article_detail_count":0,"label":1,"can_extend_detail":false,"word_type":1,"event_time":1699423810,"drift_info":null,"hotlist_param":"{\"version\":1}","word":"炎亚纶回应被公诉","word_cover":{"uri":"tos-cn-p-0004/d192708554fe47139aa10134e9557dd9_1699421233","url_list":["https://p3-sign.douyinpic.com/tos-cn-p-0004/d192708554fe47139aa10134e9557dd9_1699421233~noop.jpeg?x-expires=1699452000&x-signature=CeudnPeBzlwB%2FQGXRdGrsscRxEU%3D&from=3218412987","https://p6-sign.douyinpic.com/tos-cn-p-0004/d192708554fe47139aa10134e9557dd9_1699421233~noop.jpeg?x-expires=1699452000&x-signature=2LR%2Bgnf5ChZlgTWk5pSyHi%2BEiv0%3D&from=3218412987","https://p26-sign.douyinpic.com/tos-cn-p-0004/d192708554fe47139aa10134e9557dd9_1699421233~noop.jpeg?x-expires=1699452000&x-signature=84cwnVUOvobKuZF7Z0vAvPThHy8%3D&from=3218412987"]},"group_id":"7297445489816294719","view_count":45900436,"sentence_tag":2011},{"word_sub_board":null,"drift_info":null,"hotlist_param":"{\"version\":1}","aweme_infos":null,"sentence_tag":3002,"discuss_video_count":1,"display_style":0,"group_id":"7298302700755768610","word_type":1,"sentence_id":"1469524","event_time":1699413579,"related_words":null,"can_extend_detail":false,"view_count":42024415,"article_detail_count":0,"word":"拜登曾敦促停火以便哈方释放人质","label":0,"hot_value":8703775,"word_cover":{"uri":"tos-cn-p-0015/651183280be045ba8561521ade65c471_1699411688","url_list":["https://p6-sign.douyinpic.com/tos-cn-p-0015/651183280be045ba8561521ade65c471_1699411688~noop.jpeg?x-expires=1699452000&x-signature=o2Spzy2RvHZUWSOqbC0ElFbj3ZE%3D&from=3218412987","https://p3-sign.douyinpic.com/tos-cn-p-0015/651183280be045ba8561521ade65c471_1699411688~noop.jpeg?x-expires=1699452000&x-signature=QNhCIRkZW0x55asxol6pmw7y0SI%3D&from=3218412987","https://p11-sign.douyinpic.com/tos-cn-p-0015/651183280be045ba8561521ade65c471_1699411688~noop.jpeg?x-expires=1699452000&x-signature=ETyFMEucokocqHd9iCwTZ%2FhckWw%3D&from=3218412987"]},"position":17,"video_count":2},{"event_time":1699424705,"drift_info":null,"aweme_infos":null,"word":"我不仅泪点低","sentence_id":"1469784","display_style":0,"discuss_video_count":1,"article_detail_count":0,"label":9,"word_cover":{"uri":"tos-cn-p-0015/os6bALKD9DabSrxwHgBhXItSEAalffnAXNdA8B","url_list":["https://p11-sign.douyinpic.com/tos-cn-p-0015/os6bALKD9DabSrxwHgBhXItSEAalffnAXNdA8B~noop.jpeg?x-expires=1699452000&x-signature=%2BUvbyw0RiEgJj9LqLnIP0%2FK1tbA%3D&from=3218412987","https://p26-sign.douyinpic.com/tos-cn-p-0015/os6bALKD9DabSrxwHgBhXItSEAalffnAXNdA8B~noop.jpeg?x-expires=1699452000&x-signature=jpTUxmRv10fU%2B2N%2BBnG8Grs6X4E%3D&from=3218412987","https://p3-sign.douyinpic.com/tos-cn-p-0015/os6bALKD9DabSrxwHgBhXItSEAalffnAXNdA8B~noop.jpeg?x-expires=1699452000&x-signature=5kQmqDT%2FwmkX%2FetWP4pva7WnGuw%3D&from=3218412987"]},"video_count":1,"group_id":"7193345154769868087","can_extend_detail":false,"view_count":45489225,"hotlist_param":"{\"version\":1}","hot_value":8592116,"position":18,"word_type":1,"related_words":null,"sentence_tag":1001,"word_sub_board":[3]},{"aweme_infos":null,"sentence_tag":20002,"word_sub_board":null,"group_id":"6890490144798823684","word_type":1,"event_time":1699405807,"drift_info":null,"hotlist_param":"{\"version\":1}","display_style":0,"video_count":50,"sentence_id":"1469347","label":0,"word_cover":{"uri":"tos-cn-p-0015/da8ebe32f29c4631a348e795ae784115_1699358039","url_list":["https://p3-sign.douyinpic.com/tos-cn-p-0015/da8ebe32f29c4631a348e795ae784115_1699358039~noop.jpeg?x-expires=1699452000&x-signature=M1YNNWwV0wzz1qMocsstvXGRZr8%3D&from=3218412987","https://p26-sign.douyinpic.com/tos-cn-p-0015/da8ebe32f29c4631a348e795ae784115_1699358039~noop.jpeg?x-expires=1699452000&x-signature=bZIyS1HBUxrsXPj2PiTSFJANXJY%3D&from=3218412987","https://p11-sign.douyinpic.com/tos-cn-p-0015/da8ebe32f29c4631a348e795ae784115_1699358039~noop.jpeg?x-expires=1699452000&x-signature=oTdTsSh%2B2xVj6WNbe2xn%2B3RV4jM%3D&from=3218412987"]},"position":19,"can_extend_detail":false,"related_words":null,"view_count":40456589,"discuss_video_count":1,"word":"立冬的第一条祝福","hot_value":8575617,"article_detail_count":0},{"hot_value":8570741,"position":20,"video_count":276,"sentence_id":"1469214","view_count":40336116,"hotlist_param":"{\"version\":1}","word_cover":{"uri":"tos-cn-p-0015/e854b3d8d72f42b8befdb602f6022a3b_1699350385","url_list":["https://p26-sign.douyinpic.com/tos-cn-p-0015/e854b3d8d72f42b8befdb602f6022a3b_1699350385~noop.jpeg?x-expires=1699452000&x-signature=rXNavVAn%2Fs6Z6An5%2F0eJbGibgUY%3D&from=3218412987","https://p9-sign.douyinpic.com/tos-cn-p-0015/e854b3d8d72f42b8befdb602f6022a3b_1699350385~noop.jpeg?x-expires=1699452000&x-signature=rsjlOBnj4HQcVj3CQjP20%2BNmDgs%3D&from=3218412987","https://p3-sign.douyinpic.com/tos-cn-p-0015/e854b3d8d72f42b8befdb602f6022a3b_1699350385~noop.jpeg?x-expires=1699452000&x-signature=pHPsJ4gPW8PZcbZtlS2ysILV624%3D&from=3218412987"]},"can_extend_detail":false,"related_words":null,"aweme_infos":null,"label":0,"group_id":"6586574894257935624","event_time":1699372926,"sentence_tag":20002,"discuss_video_count":1,"word_sub_board":null,"word":"今日立冬","word_type":1,"drift_info":null,"display_style":0,"article_detail_count":0},{"article_detail_count":0,"word_cover":{"url_list":["https://p3-sign.douyinpic.com/tos-cn-p-0015/343aef6e05094bfc8267c0a74465138c_1699407292~noop.jpeg?x-expires=1699452000&x-signature=KxneFvIt8HkVm%2FYdZYqCdbjFun0%3D&from=3218412987","https://p26-sign.douyinpic.com/tos-cn-p-0015/343aef6e05094bfc8267c0a74465138c_1699407292~noop.jpeg?x-expires=1699452000&x-signature=sWS8IST6W85XTYsPNubeNNifvfc%3D&from=3218412987","https://p11-sign.douyinpic.com/tos-cn-p-0015/343aef6e05094bfc8267c0a74465138c_1699407292~noop.jpeg?x-expires=1699452000&x-signature=hgx8DI%2Bjn75nl3sgjmw1gYOzfJQ%3D&from=3218412987"],"uri":"tos-cn-p-0015/343aef6e05094bfc8267c0a74465138c_1699407292"},"position":21,"group_id":"7297373422106547467","can_extend_detail":false,"sentence_id":"1469550","drift_info":null,"display_style":0,"video_count":4,"word_type":1,"word_sub_board":null,"word":"意宴万年立冬初雪吻","hot_value":8566658,"hotlist_param":"{\"version\":1}","sentence_tag":2002,"discuss_video_count":1,"label":5,"event_time":1699414600,"related_words":null,"view_count":36221253,"aweme_infos":null},{"discuss_video_count":1,"word_sub_board":null,"label":0,"word_cover":{"uri":"tos-cn-p-0004/09b72463022a49869e3383e260b794e3_1699360494","url_list":["https://p3-sign.douyinpic.com/tos-cn-p-0004/09b72463022a49869e3383e260b794e3_1699360494~noop.jpeg?x-expires=1699452000&x-signature=4bTZ5xsomoESl62CqPHAsFnCdCE%3D&from=3218412987","https://p9-sign.douyinpic.com/tos-cn-p-0004/09b72463022a49869e3383e260b794e3_1699360494~noop.jpeg?x-expires=1699452000&x-signature=4mft0pUWt1v2rqxZOWr7T4GcGX4%3D&from=3218412987","https://p26-sign.douyinpic.com/tos-cn-p-0004/09b72463022a49869e3383e260b794e3_1699360494~noop.jpeg?x-expires=1699452000&x-signature=0o1tpR%2BvkunKI3uMnmAhDV%2BeDpQ%3D&from=3218412987"]},"drift_info":null,"sentence_tag":12000,"display_style":0,"hot_value":8553975,"group_id":"7160698633570096425","can_extend_detail":false,"sentence_id":"1469314","view_count":36720308,"aweme_infos":null,"article_detail_count":0,"word":"云顶S10爆料","video_count":5,"word_type":1,"event_time":1699403031,"hotlist_param":"{\"version\":1}","position":22,"related_words":null},{"event_time":1699421800,"related_words":null,"hot_value":8540229,"position":23,"video_count":8,"word_type":1,"drift_info":null,"sentence_tag":2002,"discuss_video_count":1,"label":5,"group_id":"7298228658643850536","sentence_id":"1469689","view_count":35370954,"hotlist_param":"{\"version\":1}","aweme_infos":null,"display_style":0,"word":"罗英子韩主任师徒开撕","word_cover":{"uri":"tos-cn-p-0015/aaec47ac7e184da487561c40e3487769_1699375344","url_list":["https://p3-sign.douyinpic.com/tos-cn-p-0015/aaec47ac7e184da487561c40e3487769_1699375344~noop.jpeg?x-expires=1699452000&x-signature=PhSDnGmD573t9tFUKyG9Varouyg%3D&from=3218412987","https://p11-sign.douyinpic.com/tos-cn-p-0015/aaec47ac7e184da487561c40e3487769_1699375344~noop.jpeg?x-expires=1699452000&x-signature=6FLwrazdhXwHNXthzPeS1ITnzYg%3D&from=3218412987","https://p26-sign.douyinpic.com/tos-cn-p-0015/aaec47ac7e184da487561c40e3487769_1699375344~noop.jpeg?x-expires=1699452000&x-signature=7YM%2FwEvVjWFehHWdI3hoDc6eCxw%3D&from=3218412987"]},"can_extend_detail":false,"word_sub_board":null,"article_detail_count":0},{"label":0,"word_cover":{"uri":"tos-cn-p-0015/os18UABcI19N6sM1ybsfVQvnlzbernvrSDDgAA","url_list":["https://p26-sign.douyinpic.com/tos-cn-p-0015/os18UABcI19N6sM1ybsfVQvnlzbernvrSDDgAA~noop.jpeg?x-expires=1699452000&x-signature=kzjw04xkUe7Wr6BqpsUig2My2T8%3D&from=3218412987","https://p3-sign.douyinpic.com/tos-cn-p-0015/os18UABcI19N6sM1ybsfVQvnlzbernvrSDDgAA~noop.jpeg?x-expires=1699452000&x-signature=TMnUSvbPuozjMV3tv0b5jHYAHNs%3D&from=3218412987","https://p6-sign.douyinpic.com/tos-cn-p-0015/os18UABcI19N6sM1ybsfVQvnlzbernvrSDDgAA~noop.jpeg?x-expires=1699452000&x-signature=h8fvob432dAOYhY%2BTgyMS1WsSR8%3D&from=3218412987"]},"can_extend_detail":false,"display_style":0,"word_sub_board":null,"hot_value":8526649,"position":24,"group_id":"7297772391865275667","hotlist_param":"{\"version\":1}","aweme_infos":null,"sentence_tag":4003,"word":"官方回应女子捂死女儿后跳楼","video_count":3,"event_time":1699413478,"view_count":33862842,"drift_info":null,"discuss_video_count":1,"word_type":1,"sentence_id":"1469522","related_words":null,"article_detail_count":0,"emo_label":0},{"word":"电影旺卡定档","word_cover":{"uri":"tos-cn-p-0015/oATA0bwLCgx9nK3QDTRDAlBCCASeIrFqlkkHfF","url_list":["https://p9-sign.douyinpic.com/tos-cn-p-0015/oATA0bwLCgx9nK3QDTRDAlBCCASeIrFqlkkHfF~noop.jpeg?x-expires=1699452000&x-signature=0TKQkdmRbMWxv7EtAmpvpm8cq48%3D&from=3218412987","https://p26-sign.douyinpic.com/tos-cn-p-0015/oATA0bwLCgx9nK3QDTRDAlBCCASeIrFqlkkHfF~noop.jpeg?x-expires=1699452000&x-signature=Rxel%2FukNTuXnJYv6n7wWTu%2BvNwQ%3D&from=3218412987","https://p3-sign.douyinpic.com/tos-cn-p-0015/oATA0bwLCgx9nK3QDTRDAlBCCASeIrFqlkkHfF~noop.jpeg?x-expires=1699452000&x-signature=M7LG4SkhImzWHOruXhReIuBDv8E%3D&from=3218412987"]},"aweme_infos":null,"sentence_tag":2001,"article_detail_count":0,"sentence_id":"1469624","hotlist_param":"{\"version\":1}","display_style":0,"discuss_video_count":1,"video_count":7,"group_id":"7276637249949013259","drift_info":null,"view_count":31887814,"label":0,"hot_value":8476965,"position":25,"can_extend_detail":false,"word_type":1,"event_time":1699417614,"related_words":null,"word_sub_board":null},{"video_count":8,"related_words":null,"view_count":29493529,"drift_info":null,"sentence_tag":4004,"word":"黄凯谈原生家庭：不期待父母的爱","position":26,"group_id":"7297408188109231379","label":3,"word_cover":{"uri":"tos-cn-p-0015/osiBVeTbdKrl8AAQEhmx9KongD9ACjBDCfSTI3","url_list":["https://p3-sign.douyinpic.com/tos-cn-p-0015/osiBVeTbdKrl8AAQEhmx9KongD9ACjBDCfSTI3~noop.jpeg?x-expires=1699452000&x-signature=WDrBsXWmfxkOIrF6oMpfNsba42M%3D&from=3218412987","https://p26-sign.douyinpic.com/tos-cn-p-0015/osiBVeTbdKrl8AAQEhmx9KongD9ACjBDCfSTI3~noop.jpeg?x-expires=1699452000&x-signature=423rqxE%2FtXUkKLu8%2BOFxpXtB4bA%3D&from=3218412987","https://p6-sign.douyinpic.com/tos-cn-p-0015/osiBVeTbdKrl8AAQEhmx9KongD9ACjBDCfSTI3~noop.jpeg?x-expires=1699452000&x-signature=yP5DElXsCCquuDPdJvwzNXSUP98%3D&from=3218412987"]},"can_extend_detail":false,"aweme_infos":null,"display_style":0,"word_sub_board":null,"hot_value":8470320,"word_type":1,"sentence_id":"1469472","event_time":1699411604,"hotlist_param":"{\"version\":1}","discuss_video_count":1,"article_detail_count":0},{"word":"雅安油罐车爆燃已致2死2伤","sentence_tag":4003,"word_sub_board":null,"hotlist_param":"{\"version\":1}","aweme_infos":null,"display_style":0,"hot_value":8409971,"position":27,"video_count":3,"group_id":"7298149638359995682","view_count":34208697,"article_detail_count":0,"discuss_video_count":1,"label":0,"word_cover":{"uri":"tos-cn-p-0015/2f9f450cd06a4d50a62c18033e8402a1_1699359981","url_list":["https://p9-sign.douyinpic.com/tos-cn-p-0015/2f9f450cd06a4d50a62c18033e8402a1_1699359981~noop.jpeg?x-expires=1699452000&x-signature=HutyUKAgSzHwb5rR6tKREdXBfHo%3D&from=3218412987","https://p26-sign.douyinpic.com/tos-cn-p-0015/2f9f450cd06a4d50a62c18033e8402a1_1699359981~noop.jpeg?x-expires=1699452000&x-signature=HkdS0kaxA8cpv6HZFOgyu%2BJglDY%3D&from=3218412987","https://p3-sign.douyinpic.com/tos-cn-p-0015/2f9f450cd06a4d50a62c18033e8402a1_1699359981~noop.jpeg?x-expires=1699452000&x-signature=uY7UZ7RDxmhy7RB1pe77qi5Yh%2B4%3D&from=3218412987"]},"can_extend_detail":false,"word_type":1,"related_words":null,"sentence_id":"1468927","event_time":1699360308,"drift_info":null},{"discuss_video_count":1,"group_id":"7298287032962700579","related_words":null,"hotlist_param":"{\"version\":1}","aweme_infos":null,"label":0,"event_time":1699411655,"drift_info":null,"display_style":0,"hot_value":8393997,"video_count":9,"sentence_tag":2001,"word_type":1,"sentence_id":"1469477","view_count":29088984,"word_sub_board":null,"word":"陈思诚张译李晨三大队再相聚","word_cover":{"uri":"tos-cn-p-0015/a07a45e7843c477596f0128b581788fd_1699406599","url_list":["https://p3-sign.douyinpic.com/tos-cn-p-0015/a07a45e7843c477596f0128b581788fd_1699406599~noop.jpeg?x-expires=1699452000&x-signature=RR3M54HcFmTqdF0HCqw%2FmELGdKg%3D&from=3218412987","https://p11-sign.douyinpic.com/tos-cn-p-0015/a07a45e7843c477596f0128b581788fd_1699406599~noop.jpeg?x-expires=1699452000&x-signature=XPViYxt7RwcMZBGAd0wLBck%2FqtQ%3D&from=3218412987","https://p26-sign.douyinpic.com/tos-cn-p-0015/a07a45e7843c477596f0128b581788fd_1699406599~noop.jpeg?x-expires=1699452000&x-signature=1odIySZn7XX6u1SDO7ZFBFdPPlI%3D&from=3218412987"]},"position":28,"can_extend_detail":false,"article_detail_count":0},{"can_extend_detail":false,"view_count":30077459,"sentence_tag":20005,"word_sub_board":null,"word_cover":{"uri":"tos-cn-p-0015/6438fe60ceb54284acf141e01b989a0f_1699322784","url_list":["https://p9-sign.douyinpic.com/tos-cn-p-0015/6438fe60ceb54284acf141e01b989a0f_1699322784~noop.jpeg?x-expires=1699452000&x-signature=C9HVfIX6pg0stEnVFPQvrDUXzGs%3D&from=3218412987","https://p3-sign.douyinpic.com/tos-cn-p-0015/6438fe60ceb54284acf141e01b989a0f_1699322784~noop.jpeg?x-expires=1699452000&x-signature=4FE2n88eV%2Fqr%2FVGp%2FFG01Y1Zg%2FM%3D&from=3218412987","https://p26-sign.douyinpic.com/tos-cn-p-0015/6438fe60ceb54284acf141e01b989a0f_1699322784~noop.jpeg?x-expires=1699452000&x-signature=01C%2B9zikfBHY%2F6p2TKL%2BXg%2Fdifk%3D&from=3218412987"]},"group_id":"7297458266790499623","aweme_infos":null,"display_style":0,"sentence_id":"1469704","hotlist_param":"{\"version\":1}","word_type":1,"event_time":1699422550,"drift_info":null,"discuss_video_count":1,"hot_value":8383433,"position":29,"video_count":10,"related_words":null,"article_detail_count":0,"word":"不是北极去不起东北更有性价比","label":1},{"video_count":1,"word_type":1,"event_time":1699372198,"drift_info":null,"hotlist_param":"{\"version\":1}","hot_value":8368779,"position":30,"can_extend_detail":false,"sentence_id":"1469199","view_count":27475075,"word_sub_board":null,"article_detail_count":0,"word_cover":{"url_list":["https://p3-sign.douyinpic.com/tos-cn-p-0015/ocABUe4yOSz6nhp79bhBkfAQgNDJACAQml7VI2~noop.jpeg?x-expires=1699452000&x-signature=NJNOXzC1rR%2BrLyilo9sl0aDfDGQ%3D&from=3218412987","https://p26-sign.douyinpic.com/tos-cn-p-0015/ocABUe4yOSz6nhp79bhBkfAQgNDJACAQml7VI2~noop.jpeg?x-expires=1699452000&x-signature=tRYzIZXH%2Byix6r4PIo%2B65WnFRlw%3D&from=3218412987","https://p9-sign.douyinpic.com/tos-cn-p-0015/ocABUe4yOSz6nhp79bhBkfAQgNDJACAQml7VI2~noop.jpeg?x-expires=1699452000&x-signature=zE0gEhrECWEcPA6U8zLIv2ixclE%3D&from=3218412987"],"uri":"tos-cn-p-0015/ocABUe4yOSz6nhp79bhBkfAQgNDJACAQml7VI2"},"group_id":"7154306588962313508","related_words":null,"aweme_infos":null,"display_style":0,"word":"JDG半决赛对战T1","sentence_tag":12000,"discuss_video_count":1,"label":3},{"word":"女儿被打父亲悬赏1万找打人者","hot_value":8210021,"sentence_id":"1469419","emo_label":0,"label":0,"position":31,"video_count":12,"group_id":"7298862809382982948","can_extend_detail":false,"view_count":23311146,"aweme_infos":null,"sentence_tag":4003,"event_time":1699410075,"word_sub_board":null,"word_cover":{"uri":"tos-cn-p-0015/f677ff524bf2423fbf5e9ccadbd174d9_1699395530","url_list":["https://p3-sign.douyinpic.com/tos-cn-p-0015/f677ff524bf2423fbf5e9ccadbd174d9_1699395530~noop.jpeg?x-expires=1699452000&x-signature=CcBOFKotVjzh77XA%2B6KH8aCrq%2Bc%3D&from=3218412987","https://p26-sign.douyinpic.com/tos-cn-p-0015/f677ff524bf2423fbf5e9ccadbd174d9_1699395530~noop.jpeg?x-expires=1699452000&x-signature=on56nC5bX9JxHRjMPQw5gu%2BH%2F8o%3D&from=3218412987","https://p11-sign.douyinpic.com/tos-cn-p-0015/f677ff524bf2423fbf5e9ccadbd174d9_1699395530~noop.jpeg?x-expires=1699452000&x-signature=%2FPdFLwHw7U3WcEkcaKbqbRiSCzk%3D&from=3218412987"]},"word_type":1,"related_words":null,"drift_info":null,"hotlist_param":"{\"version\":1}","display_style":0,"discuss_video_count":1},{"label":3,"video_count":5,"can_extend_detail":false,"event_time":1699358611,"drift_info":null,"word_cover":{"uri":"tos-cn-p-0015/4c8a29b0529c4b828e683f1f9d72dd00_1699358375","url_list":["https://p3-sign.douyinpic.com/tos-cn-p-0015/4c8a29b0529c4b828e683f1f9d72dd00_1699358375~noop.jpeg?x-expires=1699452000&x-signature=Rio4o2dxeCMGfBYV6dF%2FZtZ%2Fr1s%3D&from=3218412987","https://p26-sign.douyinpic.com/tos-cn-p-0015/4c8a29b0529c4b828e683f1f9d72dd00_1699358375~noop.jpeg?x-expires=1699452000&x-signature=ZEZzR5tJOSeHJXKK%2F4l%2BhZENjIc%3D&from=3218412987","https://p9-sign.douyinpic.com/tos-cn-p-0015/4c8a29b0529c4b828e683f1f9d72dd00_1699358375~noop.jpeg?x-expires=1699452000&x-signature=Eb5Gvnb6zAYyPC%2FsB1FzS67GQgE%3D&from=3218412987"]},"position":32,"word_type":1,"sentence_id":"1468898","related_words":null,"view_count":23503584,"hotlist_param":"{\"version\":1}","discuss_video_count":1,"word_sub_board":null,"article_detail_count":0,"word":"与主播发生关系住持被停职","hot_value":8076281,"group_id":"7296565219274560805","aweme_infos":null,"sentence_tag":4003,"display_style":0},{"word":"女子被丈夫割喉杀害 其父发声","label":3,"position":33,"view_count":22509584,"drift_info":null,"can_extend_detail":false,"related_words":null,"word_sub_board":null,"display_style":0,"group_id":"7297202031600604479","sentence_id":"1469043","event_time":1699364458,"hotlist_param":"{\"version\":1}","aweme_infos":null,"sentence_tag":4003,"hot_value":8015129,"word_cover":{"url_list":["https://p3-sign.douyinpic.com/tos-cn-p-0015/c44abc34bc8c472a9b4a0c2fbff9750f_1699362126~noop.jpeg?x-expires=1699452000&x-signature=HECm6jXuqNGon5d2qp5F8I%2FCkGE%3D&from=3218412987","https://p26-sign.douyinpic.com/tos-cn-p-0015/c44abc34bc8c472a9b4a0c2fbff9750f_1699362126~noop.jpeg?x-expires=1699452000&x-signature=JnyT7g5NORB8Spnrwnbc%2BKYa%2BSo%3D&from=3218412987","https://p6-sign.douyinpic.com/tos-cn-p-0015/c44abc34bc8c472a9b4a0c2fbff9750f_1699362126~noop.jpeg?x-expires=1699452000&x-signature=JvwRJz0c0EGTiKu177turOTxXNE%3D&from=3218412987"],"uri":"tos-cn-p-0015/c44abc34bc8c472a9b4a0c2fbff9750f_1699362126"},"video_count":7,"word_type":1,"discuss_video_count":1,"article_detail_count":0},{"discuss_video_count":1,"word_cover":{"uri":"tos-cn-p-0015/95f9a73151384ef995ae0d76aa08cabe_1699408909","url_list":["https://p26-sign.douyinpic.com/tos-cn-p-0015/95f9a73151384ef995ae0d76aa08cabe_1699408909~noop.jpeg?x-expires=1699452000&x-signature=gQi1e13chLqH8ZikvHyI42ommGs%3D&from=3218412987","https://p3-sign.douyinpic.com/tos-cn-p-0015/95f9a73151384ef995ae0d76aa08cabe_1699408909~noop.jpeg?x-expires=1699452000&x-signature=FADmPvRL9UtMqUlbEiAB8SI9JYs%3D&from=3218412987","https://p6-sign.douyinpic.com/tos-cn-p-0015/95f9a73151384ef995ae0d76aa08cabe_1699408909~noop.jpeg?x-expires=1699452000&x-signature=3Qr3sDE6JHQjf1a8VNt1KKhVqVk%3D&from=3218412987"]},"position":34,"video_count":5,"drift_info":null,"hotlist_param":"{\"version\":1}","aweme_infos":null,"display_style":0,"article_detail_count":0,"word":"资方让刘德华红毯先生定档春节","label":0,"hot_value":7991261,"group_id":"7298288364347266319","can_extend_detail":false,"view_count":22529076,"word_sub_board":null,"word_type":1,"sentence_id":"1469471","event_time":1699411569,"related_words":null,"sentence_tag":2001},{"discuss_video_count":1,"word_sub_board":null,"group_id":"7296862743893251365","display_style":0,"drift_info":null,"aweme_infos":null,"article_detail_count":0,"position":35,"video_count":1,"can_extend_detail":false,"word_type":1,"sentence_id":"1469864","event_time":1699427245,"view_count":20126070,"hot_value":7988484,"word_cover":{"uri":"tos-cn-p-0015/okaxlck74EiPBDHBhKhA4ezCfeNBAC8mRI4Lla","url_list":["https://p9-sign.douyinpic.com/tos-cn-p-0015/okaxlck74EiPBDHBhKhA4ezCfeNBAC8mRI4Lla~noop.jpeg?x-expires=1699452000&x-signature=O4ORy9UVVef0Pb9eGGAommxVJHw%3D&from=3218412987","https://p6-sign.douyinpic.com/tos-cn-p-0015/okaxlck74EiPBDHBhKhA4ezCfeNBAC8mRI4Lla~noop.jpeg?x-expires=1699452000&x-signature=sEgPhdf4K6Lju5Gs3x0r64s8Ujg%3D&from=3218412987","https://p3-sign.douyinpic.com/tos-cn-p-0015/okaxlck74EiPBDHBhKhA4ezCfeNBAC8mRI4Lla~noop.jpeg?x-expires=1699452000&x-signature=EjPA5YI2GyQrGNErdAHiI8sjzrE%3D&from=3218412987"]},"related_words":null,"hotlist_param":"{\"version\":1}","sentence_tag":2003,"word":"苏醒到底知道多少兄弟家密码","label":1},{"related_words":null,"drift_info":null,"aweme_infos":null,"word_sub_board":null,"article_detail_count":0,"label":0,"position":36,"event_time":1699408367,"view_count":18115444,"discuss_video_count":1,"sentence_tag":20002,"hot_value":7985964,"video_count":3,"can_extend_detail":false,"word_type":1,"sentence_id":"1469387","word":"没想到冬天里的泡泡这么美","word_cover":{"url_list":["https://p3-sign.douyinpic.com/tos-cn-p-0015/oY3irMBHEDzUCLJAFXlAInHBSIxfCMubgAVeZ9~noop.jpeg?x-expires=1699452000&x-signature=gziiNk0F13WOOfWUVrWtgbBIoN0%3D&from=3218412987","https://p11-sign.douyinpic.com/tos-cn-p-0015/oY3irMBHEDzUCLJAFXlAInHBSIxfCMubgAVeZ9~noop.jpeg?x-expires=1699452000&x-signature=OdJ2idsnVzTfe6aaDsz1A6FyiIo%3D&from=3218412987","https://p26-sign.douyinpic.com/tos-cn-p-0015/oY3irMBHEDzUCLJAFXlAInHBSIxfCMubgAVeZ9~noop.jpeg?x-expires=1699452000&x-signature=Tr6FdLYW4TmIw1i7r41igtKhmQE%3D&from=3218412987"],"uri":"tos-cn-p-0015/oY3irMBHEDzUCLJAFXlAInHBSIxfCMubgAVeZ9"},"group_id":"7296795159336277299","hotlist_param":"{\"version\":1}","display_style":0},{"position":37,"group_id":"7297389563101926668","word_type":1,"related_words":null,"view_count":16265405,"drift_info":null,"label":9,"hot_value":7972121,"aweme_infos":null,"discuss_video_count":1,"sentence_tag":1001,"word_cover":{"uri":"tos-cn-p-0015/d8bda7f806024426b57389fa1ec64771_1699259636","url_list":["https://p3-sign.douyinpic.com/tos-cn-p-0015/d8bda7f806024426b57389fa1ec64771_1699259636~noop.jpeg?x-expires=1699452000&x-signature=S9JNvLHk4ly2r3KDQiOH%2Bcfo1sM%3D&from=3218412987","https://p6-sign.douyinpic.com/tos-cn-p-0015/d8bda7f806024426b57389fa1ec64771_1699259636~noop.jpeg?x-expires=1699452000&x-signature=paC7RXpJn6fgbBw2zEr5wBsP3tg%3D&from=3218412987","https://p26-sign.douyinpic.com/tos-cn-p-0015/d8bda7f806024426b57389fa1ec64771_1699259636~noop.jpeg?x-expires=1699452000&x-signature=N0n4tkmisxlWtV5uYxzd3lquJb0%3D&from=3218412987"]},"event_time":1699411428,"can_extend_detail":false,"hotlist_param":"{\"version\":1}","article_detail_count":0,"word":"兜兜转转快闪回顾","video_count":11,"word_sub_board":[3],"sentence_id":"1469463","display_style":0},{"group_id":"7296675582199403786","label":12,"hot_value":7858309,"word_cover":{"uri":"tos-cn-p-0015/ogRBbtnyeKSVk5JNe7PgAC1BYWqIQGAbAKec3D","url_list":["https://p3-sign.douyinpic.com/tos-cn-p-0015/ogRBbtnyeKSVk5JNe7PgAC1BYWqIQGAbAKec3D~noop.jpeg?x-expires=1699452000&x-signature=WHWOe1lgYNTHJGWbshzayZTKLKQ%3D&from=3218412987","https://p11-sign.douyinpic.com/tos-cn-p-0015/ogRBbtnyeKSVk5JNe7PgAC1BYWqIQGAbAKec3D~noop.jpeg?x-expires=1699452000&x-signature=%2BQsAFNG2O1n7z4pifNIMvNGOpQU%3D&from=3218412987","https://p9-sign.douyinpic.com/tos-cn-p-0015/ogRBbtnyeKSVk5JNe7PgAC1BYWqIQGAbAKec3D~noop.jpeg?x-expires=1699452000&x-signature=iKSAe2U0YC4rAgVW26TiYAs0FNo%3D&from=3218412987"]},"video_count":2,"sentence_tag":2001,"display_style":0,"word_sub_board":null,"emo_label":0,"sentence_id":"1468820","event_time":1699356529,"hotlist_param":"{\"version\":1}","aweme_infos":null,"discuss_video_count":1,"can_extend_detail":false,"word_type":1,"related_words":null,"drift_info":null,"word":"张译断崖式转行","position":38,"view_count":14989967,"article_detail_count":0},{"label":5,"hot_value":7856237,"word_cover":{"uri":"tos-cn-p-0015/o0alZanbHAMDC9pegI8ySNNnHbeUpXJDAAB6RQ","url_list":["https://p3-sign.douyinpic.com/tos-cn-p-0015/o0alZanbHAMDC9pegI8ySNNnHbeUpXJDAAB6RQ~noop.jpeg?x-expires=1699452000&x-signature=fP5ET1g15JxywT2LqJo8nUjHkBs%3D&from=3218412987","https://p26-sign.douyinpic.com/tos-cn-p-0015/o0alZanbHAMDC9pegI8ySNNnHbeUpXJDAAB6RQ~noop.jpeg?x-expires=1699452000&x-signature=vKwaP%2BJQXtPx%2FdXs5WknvMkPaMI%3D&from=3218412987","https://p11-sign.douyinpic.com/tos-cn-p-0015/o0alZanbHAMDC9pegI8ySNNnHbeUpXJDAAB6RQ~noop.jpeg?x-expires=1699452000&x-signature=7oU8elW%2FHGerq1Wxpo6flaIcm90%3D&from=3218412987"]},"video_count":58,"word_type":1,"event_time":1699413795,"hotlist_param":"{\"version\":1}","word_sub_board":null,"article_detail_count":0,"position":39,"sentence_id":"1469531","related_words":null,"view_count":14550552,"drift_info":null,"aweme_infos":null,"sentence_tag":5000,"display_style":0,"discuss_video_count":1,"word":"金秋挑战野钓大板鲫","group_id":"7298673156783691044","can_extend_detail":false},{"view_count":13865747,"sentence_tag":2002,"hot_value":7854566,"can_extend_detail":false,"related_words":null,"drift_info":null,"display_style":0,"discuss_video_count":1,"article_detail_count":0,"label":5,"position":40,"video_count":8,"group_id":"7297428258743637260","event_time":1699424299,"word_sub_board":null,"word":"宁安如梦极限N选1","word_cover":{"url_list":["https://p26-sign.douyinpic.com/tos-cn-p-0015/41193e8a5a654cb6823bc268bbd214fb_1699421380~noop.jpeg?x-expires=1699452000&x-signature=ll0MgM7rw4XP79Rz9VxXQroTUP8%3D&from=3218412987","https://p3-sign.douyinpic.com/tos-cn-p-0015/41193e8a5a654cb6823bc268bbd214fb_1699421380~noop.jpeg?x-expires=1699452000&x-signature=Txm71QhGmsJjKhPVUi2F6I%2FTEJ0%3D&from=3218412987","https://p6-sign.douyinpic.com/tos-cn-p-0015/41193e8a5a654cb6823bc268bbd214fb_1699421380~noop.jpeg?x-expires=1699452000&x-signature=WdYX%2Bvii%2BKHy7zO2%2B293QXkSunw%3D&from=3218412987"],"uri":"tos-cn-p-0015/41193e8a5a654cb6823bc268bbd214fb_1699421380"},"word_type":1,"sentence_id":"1469765","hotlist_param":"{\"version\":1}","aweme_infos":null},{"discuss_video_count":1,"word_sub_board":null,"word":"你用9键还是26键","video_count":1,"related_words":null,"sentence_tag":18000,"sentence_id":"1469208","view_count":11311391,"aweme_infos":null,"word_cover":{"url_list":["https://p3-sign.douyinpic.com/tos-cn-p-0015/2e56de2a6ecf4971b18242d79224729a_1699178172~noop.jpeg?x-expires=1699452000&x-signature=vvz62JtdP6ngdRtCX0Y2NvGOLWQ%3D&from=3218412987","https://p26-sign.douyinpic.com/tos-cn-p-0015/2e56de2a6ecf4971b18242d79224729a_1699178172~noop.jpeg?x-expires=1699452000&x-signature=gAf84Gp9KArAk5zCsqyRd9m7VJM%3D&from=3218412987","https://p11-sign.douyinpic.com/tos-cn-p-0015/2e56de2a6ecf4971b18242d79224729a_1699178172~noop.jpeg?x-expires=1699452000&x-signature=nJ0jN6aXYaM8bnlayuB0K9ece7U%3D&from=3218412987"],"uri":"tos-cn-p-0015/2e56de2a6ecf4971b18242d79224729a_1699178172"},"position":41,"group_id":"6671202645396428043","word_type":1,"display_style":0,"article_detail_count":0,"label":0,"can_extend_detail":false,"event_time":1699372495,"hotlist_param":"{\"version\":1}","hot_value":7800067,"drift_info":null},{"label":0,"group_id":"7298271264052679988","can_extend_detail":false,"related_words":null,"discuss_video_count":1,"article_detail_count":0,"hot_value":7796913,"word_cover":{"uri":"tos-cn-p-0015/68945a6f49dc48cf9c3c05babbe5474c_1699394617","url_list":["https://p9-sign.douyinpic.com/tos-cn-p-0015/68945a6f49dc48cf9c3c05babbe5474c_1699394617~noop.jpeg?x-expires=1699452000&x-signature=FzWsYrfYTbU4JDpptH0WPbAzGm8%3D&from=3218412987","https://p26-sign.douyinpic.com/tos-cn-p-0015/68945a6f49dc48cf9c3c05babbe5474c_1699394617~noop.jpeg?x-expires=1699452000&x-signature=bB3n1ghuKKps5S15Huy6l96baUg%3D&from=3218412987","https://p3-sign.douyinpic.com/tos-cn-p-0015/68945a6f49dc48cf9c3c05babbe5474c_1699394617~noop.jpeg?x-expires=1699452000&x-signature=49wWdkVMi1dITJwOZikdBYzvJRE%3D&from=3218412987"]},"position":42,"word_type":1,"hotlist_param":"{\"version\":1}","word":"巴萨0:1不敌矿工","drift_info":null,"sentence_tag":5000,"word_sub_board":null,"video_count":12,"sentence_id":"1469335","event_time":1699405179,"view_count":10871294,"aweme_infos":null,"display_style":0},{"related_words":null,"word_sub_board":null,"article_detail_count":0,"hot_value":7742067,"video_count":3,"group_id":"7297428331485566227","hotlist_param":"{\"version\":1}","sentence_tag":2002,"word":"罗英子喜提富二代同事","can_extend_detail":false,"drift_info":null,"event_time":1699411687,"view_count":9736418,"aweme_infos":null,"display_style":0,"discuss_video_count":1,"word_cover":{"uri":"tos-cn-p-0015/ogtAN0nW8foCSIKgf9DYABZA8l2QgDCbglitkD","url_list":["https://p26-sign.douyinpic.com/tos-cn-p-0015/ogtAN0nW8foCSIKgf9DYABZA8l2QgDCbglitkD~noop.jpeg?x-expires=1699452000&x-signature=MUSo9rugQi0ZiXR3r31NgIDK%2FhY%3D&from=3218412987","https://p3-sign.douyinpic.com/tos-cn-p-0015/ogtAN0nW8foCSIKgf9DYABZA8l2QgDCbglitkD~noop.jpeg?x-expires=1699452000&x-signature=KlOBJE39mQXlPEbSXbpqx6qNco0%3D&from=3218412987","https://p11-sign.douyinpic.com/tos-cn-p-0015/ogtAN0nW8foCSIKgf9DYABZA8l2QgDCbglitkD~noop.jpeg?x-expires=1699452000&x-signature=bWIzmtKVNMWc59iTk3SOr6bClWg%3D&from=3218412987"]},"word_type":1,"sentence_id":"1469479","label":5,"position":43},{"discuss_video_count":1,"word":"游戏玩家的闭环","position":44,"word_type":1,"sentence_id":"1469414","related_words":null,"drift_info":null,"aweme_infos":null,"hot_value":7679151,"word_cover":{"uri":"tos-cn-p-0015/a97a59c9ffcb41cba91d7002c486acc1_1699351455","url_list":["https://p11-sign.douyinpic.com/tos-cn-p-0015/a97a59c9ffcb41cba91d7002c486acc1_1699351455~noop.jpeg?x-expires=1699452000&x-signature=II3haOjpqwT8nqpvLtpTdtxZhyY%3D&from=3218412987","https://p26-sign.douyinpic.com/tos-cn-p-0015/a97a59c9ffcb41cba91d7002c486acc1_1699351455~noop.jpeg?x-expires=1699452000&x-signature=UfpAw2dd8d4z%2FnMqQt7%2Fu2iYbh4%3D&from=3218412987","https://p3-sign.douyinpic.com/tos-cn-p-0015/a97a59c9ffcb41cba91d7002c486acc1_1699351455~noop.jpeg?x-expires=1699452000&x-signature=ZsHTvyEBPH%2BPsylGLylY9QSWLjs%3D&from=3218412987"]},"event_time":1699409927,"hotlist_param":"{\"version\":1}","sentence_tag":18000,"display_style":0,"article_detail_count":0,"group_id":"7297168056064103734","can_extend_detail":false,"label":0,"video_count":1,"view_count":7158474,"word_sub_board":null},{"word":"冬天第一杯奶茶","video_count":3,"word_sub_board":null,"word_cover":{"uri":"tos-cn-p-0015/owrCAQIh9Cst3e9dbgBGmIsSEAtlHJzp4Z3AfB","url_list":["https://p3-sign.douyinpic.com/tos-cn-p-0015/owrCAQIh9Cst3e9dbgBGmIsSEAtlHJzp4Z3AfB~noop.jpeg?x-expires=1699452000&x-signature=aQGcFRbNVoIuTqxtMo6lidQGDBU%3D&from=3218412987","https://p26-sign.douyinpic.com/tos-cn-p-0015/owrCAQIh9Cst3e9dbgBGmIsSEAtlHJzp4Z3AfB~noop.jpeg?x-expires=1699452000&x-signature=Zc9FxYUYKu4Vh93r3qvNroTmGSg%3D&from=3218412987","https://p6-sign.douyinpic.com/tos-cn-p-0015/owrCAQIh9Cst3e9dbgBGmIsSEAtlHJzp4Z3AfB~noop.jpeg?x-expires=1699452000&x-signature=vvlXCOin4tyzZaumGxRYMQVTjZ4%3D&from=3218412987"]},"can_extend_detail":false,"sentence_id":"1469796","event_time":1699425152,"hotlist_param":"{\"version\":1}","label":1,"hot_value":7637464,"group_id":"6745319070641427716","word_type":1,"sentence_tag":20002,"article_detail_count":0,"discuss_video_count":1,"position":45,"related_words":null,"view_count":6202362,"drift_info":null,"aweme_infos":null,"display_style":0},{"aweme_infos":null,"article_detail_count":0,"label":5,"word_cover":{"uri":"tos-cn-p-0015/o8xBobKUnAK7n4tQDIODADCGrBleITf7KuexRS","url_list":["https://p3-sign.douyinpic.com/tos-cn-p-0015/o8xBobKUnAK7n4tQDIODADCGrBleITf7KuexRS~noop.jpeg?x-expires=1699452000&x-signature=MIxzyUKG9G%2F9tVnSzc%2BY7RAHq80%3D&from=3218412987","https://p9-sign.douyinpic.com/tos-cn-p-0015/o8xBobKUnAK7n4tQDIODADCGrBleITf7KuexRS~noop.jpeg?x-expires=1699452000&x-signature=7oI1RoEN9spprXkqv3LttdGKdsU%3D&from=3218412987","https://p26-sign.douyinpic.com/tos-cn-p-0015/o8xBobKUnAK7n4tQDIODADCGrBleITf7KuexRS~noop.jpeg?x-expires=1699452000&x-signature=3EpZ3CZYIKeH3Npa1O%2BHX5Tnau8%3D&from=3218412987"]},"position":46,"drift_info":null,"word_sub_board":null,"group_id":"7297431366744233235","related_words":null,"view_count":5362626,"can_extend_detail":false,"word_type":1,"event_time":1699414689,"hotlist_param":"{\"version\":1}","sentence_tag":2002,"word":"宁安如梦翁虹演白鹿母亲","hot_value":7623378,"video_count":2,"display_style":0,"discuss_video_count":1,"sentence_id":"1469554"},{"word":"请查收你的闺蜜姜珮瑶","video_count":10,"related_words":null,"hotlist_param":"{\"version\":1}","discuss_video_count":1,"article_detail_count":0,"hot_value":7619590,"group_id":"7297421609156908329","can_extend_detail":false,"word_type":1,"event_time":1699421696,"view_count":3990830,"label":1,"position":47,"drift_info":null,"word_cover":{"url_list":["https://p3-sign.douyinpic.com/tos-cn-p-0015/okSLECByAg7IkZe6UhHptBHALB0zpfBVYN6CaA~noop.jpeg?x-expires=1699452000&x-signature=lFbg6%2FI0nTJgSi9ZRWVW%2BE5bMzg%3D&from=3218412987","https://p26-sign.douyinpic.com/tos-cn-p-0015/okSLECByAg7IkZe6UhHptBHALB0zpfBVYN6CaA~noop.jpeg?x-expires=1699452000&x-signature=iUaxpmgFxjCniqdezHf33IkUMXI%3D&from=3218412987","https://p6-sign.douyinpic.com/tos-cn-p-0015/okSLECByAg7IkZe6UhHptBHALB0zpfBVYN6CaA~noop.jpeg?x-expires=1699452000&x-signature=9B%2BFS7j%2Bu%2F%2Fa56PaOrhGcxF3lVc%3D&from=3218412987"],"uri":"tos-cn-p-0015/okSLECByAg7IkZe6UhHptBHALB0zpfBVYN6CaA"},"sentence_id":"1469683","aweme_infos":null,"sentence_tag":2002,"display_style":0,"word_sub_board":null},{"drift_info":null,"article_detail_count":0,"hot_value":7583379,"group_id":"7297178916124677388","can_extend_detail":false,"view_count":2249058,"sentence_id":"1469501","event_time":1699412599,"word_sub_board":null,"word":"白鹿王星越宁安如梦是be","word_cover":{"uri":"tos-cn-p-0015/2053d5c34e8b49158c3a09f3f63e5323_1699362258","url_list":["https://p3-sign.douyinpic.com/tos-cn-p-0015/2053d5c34e8b49158c3a09f3f63e5323_1699362258~noop.jpeg?x-expires=1699452000&x-signature=wu5gqwzJVlsNDYz0gYS9nESNmRU%3D&from=3218412987","https://p9-sign.douyinpic.com/tos-cn-p-0015/2053d5c34e8b49158c3a09f3f63e5323_1699362258~noop.jpeg?x-expires=1699452000&x-signature=YxJBPq4IZJ4FJatRxDAKMoyiXjM%3D&from=3218412987","https://p6-sign.douyinpic.com/tos-cn-p-0015/2053d5c34e8b49158c3a09f3f63e5323_1699362258~noop.jpeg?x-expires=1699452000&x-signature=0HneGptZUUDbvrnQYG1qxCyacAg%3D&from=3218412987"]},"video_count":3,"word_type":1,"position":48,"hotlist_param":"{\"version\":1}","sentence_tag":2002,"discuss_video_count":1,"label":0,"related_words":null,"aweme_infos":null,"display_style":0},{"hot_value":7581374,"display_style":0,"word_sub_board":null,"event_time":1699414896,"related_words":null,"view_count":1153230,"discuss_video_count":1,"group_id":"7297388930830488843","word_type":1,"sentence_id":"1469560","position":49,"sentence_tag":11000,"article_detail_count":0,"video_count":1,"can_extend_detail":false,"drift_info":null,"hotlist_param":"{\"version\":1}","aweme_infos":null,"word":"何小鹏回应余承东AEB之争","label":0,"word_cover":{"uri":"tos-cn-p-0015/oUoHCbpJnASleb0AVVDevlIJSBDQuaJgMt9ViA","url_list":["https://p26-sign.douyinpic.com/tos-cn-p-0015/oUoHCbpJnASleb0AVVDevlIJSBDQuaJgMt9ViA~noop.jpeg?x-expires=1699452000&x-signature=WEW34%2BRUhRf8%2FvrimMbjNwY%2B%2B7o%3D&from=3218412987","https://p11-sign.douyinpic.com/tos-cn-p-0015/oUoHCbpJnASleb0AVVDevlIJSBDQuaJgMt9ViA~noop.jpeg?x-expires=1699452000&x-signature=IrkBxvzyuU3OVd7opCk35BU25sk%3D&from=3218412987","https://p3-sign.douyinpic.com/tos-cn-p-0015/oUoHCbpJnASleb0AVVDevlIJSBDQuaJgMt9ViA~noop.jpeg?x-expires=1699452000&x-signature=Vw9sTp1gdmElLXDs%2BG4pQosf2Eg%3D&from=3218412987"]}},{"view_count":2287980,"word":"无所畏惧韩主任被拿捏住了","sentence_id":"1469473","aweme_infos":null,"sentence_tag":2002,"word_cover":{"uri":"tos-cn-p-0015/cf04795fa0d14ce59a26bcdad2cf03de_1699289150","url_list":["https://p9-sign.douyinpic.com/tos-cn-p-0015/cf04795fa0d14ce59a26bcdad2cf03de_1699289150~noop.jpeg?x-expires=1699452000&x-signature=0R%2BNd4x8tltLUxsIt99cXvYsS3c%3D&from=3218412987","https://p3-sign.douyinpic.com/tos-cn-p-0015/cf04795fa0d14ce59a26bcdad2cf03de_1699289150~noop.jpeg?x-expires=1699452000&x-signature=VBETMLBPQXohgXo%2FAzslC%2FM6aHM%3D&from=3218412987","https://p6-sign.douyinpic.com/tos-cn-p-0015/cf04795fa0d14ce59a26bcdad2cf03de_1699289150~noop.jpeg?x-expires=1699452000&x-signature=w8ybdDPa7SnBOagPZPzuAq1CfI0%3D&from=3218412987"]},"hotlist_param":"{\"version\":1}","related_words":null,"drift_info":null,"discuss_video_count":1,"word_sub_board":null,"article_detail_count":0,"hot_value":7575693,"group_id":"7298494487244051775","video_count":4,"can_extend_detail":false,"word_type":1,"event_time":1699411611,"display_style":0,"label":0,"position":50}],"active_time":"2023-11-08 16:23:37","share_info":{"share_url":"https://www.iesdouyin.com/share/billboard/?id=0","share_title":"我在看抖音热榜，发现最火的内容，赶快来看！","share_link_desc":"我在看抖音热榜，发现最火的内容，赶快来看！戳这里>>"},"trending_list":[{"sentence_tag":2002,"article_detail_count":0,"group_id":"7298030172011418895","word_type":3,"related_words":null,"aweme_infos":null,"label":5,"video_count":9,"drift_info":null,"hotlist_param":"{\"version\":1}","display_style":0,"word":"以爱为营意宴万年初吻","event_time":1699355137,"sentence_id":"1468787","discuss_video_count":1,"word_sub_board":null,"hot_value":0,"word_cover":{"uri":"tos-cn-p-0015/o0CKc34DYM9fBQcIHB8lADlngMNbeAaibgSAor","url_list":["https://p3-sign.douyinpic.com/tos-cn-p-0015/o0CKc34DYM9fBQcIHB8lADlngMNbeAaibgSAor~noop.jpeg?x-expires=1699452000&x-signature=9deMd3N4BEIhdh8Jr6uk%2B%2BnJaNk%3D&from=3218412987","https://p26-sign.douyinpic.com/tos-cn-p-0015/o0CKc34DYM9fBQcIHB8lADlngMNbeAaibgSAor~noop.jpeg?x-expires=1699452000&x-signature=OBM%2F6rzNDXzahnV2wPKE%2B%2B%2Fa3Lk%3D&from=3218412987","https://p11-sign.douyinpic.com/tos-cn-p-0015/o0CKc34DYM9fBQcIHB8lADlngMNbeAaibgSAor~noop.jpeg?x-expires=1699452000&x-signature=mQXfKWX83SoJCPC%2B6WdDoAxI4vM%3D&from=3218412987"]}},{"word_cover":{"uri":"tos-cn-p-0015/b727591c160b4129ae562bfa74911f77_1699351212","url_list":["https://p11-sign.douyinpic.com/tos-cn-p-0015/b727591c160b4129ae562bfa74911f77_1699351212~noop.jpeg?x-expires=1699452000&x-signature=srsXAebkCEU%2B23chF0J8zhbtElU%3D&from=3218412987","https://p3-sign.douyinpic.com/tos-cn-p-0015/b727591c160b4129ae562bfa74911f77_1699351212~noop.jpeg?x-expires=1699452000&x-signature=rxVGvAMk4KRmERwwL%2F47DmEKqH4%3D&from=3218412987","https://p9-sign.douyinpic.com/tos-cn-p-0015/b727591c160b4129ae562bfa74911f77_1699351212~noop.jpeg?x-expires=1699452000&x-signature=gXO1IcGHvs9VMPnklWcoEZ8E1o8%3D&from=3218412987"]},"group_id":"7295288955984516415","aweme_infos":null,"sentence_tag":1001,"word":"迷人的天蝎不会说情话","display_style":0,"discuss_video_count":1,"hotlist_param":"{\"version\":1}","word_sub_board":[3],"label":0,"hot_value":0,"video_count":27,"sentence_id":"1469758","event_time":1699424144,"related_words":null,"article_detail_count":0,"word_type":3,"drift_info":null},{"drift_info":null,"sentence_tag":12000,"display_style":0,"hot_value":0,"group_id":"6919305142697809156","aweme_infos":null,"word":"原神 罪人舞步旋","hotlist_param":"{\"version\":1}","related_words":null,"discuss_video_count":1,"word_sub_board":null,"video_count":2,"event_time":1699411370,"word_type":3,"sentence_id":"1469469","label":0,"word_cover":{"uri":"tos-cn-p-0015/87526a545a0c47d5b7db4d83cc2a7bfa_1699345479","url_list":["https://p11-sign.douyinpic.com/tos-cn-p-0015/87526a545a0c47d5b7db4d83cc2a7bfa_1699345479~noop.jpeg?x-expires=1699452000&x-signature=9vhY9PqQZH%2BtYFe7GtvkeJYWbnE%3D&from=3218412987","https://p3-sign.douyinpic.com/tos-cn-p-0015/87526a545a0c47d5b7db4d83cc2a7bfa_1699345479~noop.jpeg?x-expires=1699452000&x-signature=wYY2AheYYJScrVlq7FEPJTjjIJI%3D&from=3218412987","https://p9-sign.douyinpic.com/tos-cn-p-0015/87526a545a0c47d5b7db4d83cc2a7bfa_1699345479~noop.jpeg?x-expires=1699452000&x-signature=t3weBC7ftwjG9PGS%2BbI4%2B0S1KlA%3D&from=3218412987"]}},{"aweme_infos":null,"article_detail_count":0,"word_type":3,"word_cover":{"uri":"tos-cn-p-0015/9736030b50084412ae731a53cbbe6d0f_1699401558","url_list":["https://p11-sign.douyinpic.com/tos-cn-p-0015/9736030b50084412ae731a53cbbe6d0f_1699401558~noop.jpeg?x-expires=1699452000&x-signature=hwLtplBkxiPMCH7ALYvex3ne1NM%3D&from=3218412987","https://p3-sign.douyinpic.com/tos-cn-p-0015/9736030b50084412ae731a53cbbe6d0f_1699401558~noop.jpeg?x-expires=1699452000&x-signature=8czDqvPic84VmxNO9JQ1UBmT1kc%3D&from=3218412987","https://p26-sign.douyinpic.com/tos-cn-p-0015/9736030b50084412ae731a53cbbe6d0f_1699401558~noop.jpeg?x-expires=1699452000&x-signature=90eR0Nkju7dtq7hKDyUUvHhSapw%3D&from=3218412987"]},"video_count":1,"discuss_video_count":1,"hot_value":0,"label":0,"sentence_id":"1469287","event_time":1699401749,"related_words":null,"drift_info":null,"hotlist_param":"{\"version\":1}","sentence_tag":8000,"word":"哈师大天鹅又被冻在湖里了","display_style":0,"word_sub_board":null,"group_id":"7298866096177501481"},{"related_words":null,"drift_info":null,"hotlist_param":"{\"version\":1}","display_style":0,"discuss_video_count":1,"word":"电影热搜一顿饭八百个心眼","word_sub_board":null,"hot_value":0,"video_count":2,"event_time":1699414564,"article_detail_count":0,"aweme_infos":null,"sentence_tag":2001,"label":8,"word_cover":{"url_list":["https://p6-sign.douyinpic.com/tos-cn-p-0015/oE9AVJ8S5Enng5BAibrgbnDflKIa90fANKKmaB~noop.jpeg?x-expires=1699452000&x-signature=JuB5jWWIVf1uKdYR0i4YL0puR%2BE%3D&from=3218412987","https://p3-sign.douyinpic.com/tos-cn-p-0015/oE9AVJ8S5Enng5BAibrgbnDflKIa90fANKKmaB~noop.jpeg?x-expires=1699452000&x-signature=F0AJX5ryE1gAkTjZyGnYKgBEWD0%3D&from=3218412987","https://p26-sign.douyinpic.com/tos-cn-p-0015/oE9AVJ8S5Enng5BAibrgbnDflKIa90fANKKmaB~noop.jpeg?x-expires=1699452000&x-signature=hGRiMoGUfAOFNzHC%2FRF64X1bRjI%3D&from=3218412987"],"uri":"tos-cn-p-0015/oE9AVJ8S5Enng5BAibrgbnDflKIa90fANKKmaB"},"group_id":"7297418099249239337","word_type":3,"sentence_id":"1469548"}],"trending_desc":"实时上升热点","recommend_list":null},"ad_search_list":null,"banner_dark":{"uri":"32e5200049fac86168117","url_list":["https://p9-sign.douyinpic.com/obj/32e5200049fac86168117?x-expires=1699452000&x-signature=XFLWYvLpeY3nfF98J3PqkMxFq94%3D&from=65706370","https://p3-sign.douyinpic.com/obj/32e5200049fac86168117?x-expires=1699452000&x-signature=GtwGqWZowWgRTCAbikK2bHO4Fm4%3D&from=65706370","https://p11-sign.douyinpic.com/obj/32e5200049fac86168117?x-expires=1699452000&x-signature=j%2BbSY42tCmB2F%2Fg9zfGuhs3V05I%3D&from=65706370"]},"banner_light":{"uri":"321f4000f703369c24604","url_list":["https://p26-sign.douyinpic.com/obj/321f4000f703369c24604?x-expires=1699452000&x-signature=m4jhSlb9DxxWMR3qhKb%2FYOOHRek%3D&from=65706370","https://p9-sign.douyinpic.com/obj/321f4000f703369c24604?x-expires=1699452000&x-signature=8dU8%2FOvU9LqU810qpZGJOhsNOpM%3D&from=65706370","https://p3-sign.douyinpic.com/obj/321f4000f703369c24604?x-expires=1699452000&x-signature=XwyDoSTfpVzIXu0wQUdq5cHPS3w%3D&from=65706370"]}}
